[
  {
    "id": "23",
    "name": "Patchwerk Normal",
    "rankings": []
  },
  {
    "id": "28",
    "name": "Grobbulus Normal",
    "rankings": [
      {
        "name": "Bunlop",
        "class": "Priest",
        "rank": 1
      },
      {
        "name": "Dagomi",
        "class": "Paladin",
        "rank": 2
      },
      {
        "name": "Holyymolyy",
        "class": "Priest",
        "rank": 3
      },
      {
        "name": "Moonwell",
        "class": "Druid",
        "rank": 4
      },
      {
        "name": "Aamara",
        "class": "Priest",
        "rank": 5
      },
      {
        "name": "Msstorm",
        "class": "Priest",
        "rank": 6
      },
      {
        "name": "Trendkill",
        "class": "Paladin",
        "rank": 7
      },
      {
        "name": "Fannia",
        "class": "Druid",
        "rank": 8
      },
      {
        "name": "Shalawam",
        "class": "Priest",
        "rank": 9
      },
      {
        "name": "Kasiri",
        "class": "Priest",
        "rank": 10
      },
      {
        "name": "Palamino",
        "class": "Paladin",
        "rank": 11
      },
      {
        "name": "Snormantha",
        "class": "Priest",
        "rank": 12
      },
      {
        "name": "Lilianas",
        "class": "Rogue",
        "rank": 13
      },
      {
        "name": "Taniel",
        "class": "Warrior",
        "rank": 14
      },
      {
        "name": "Iculus",
        "class": "Warrior",
        "rank": 15
      },
      {
        "name": "Alexanderr",
        "class": "Warrior",
        "rank": 16
      },
      {
        "name": "Loafofbread",
        "class": "Warrior",
        "rank": 17
      },
      {
        "name": "Oars",
        "class": "Warrior",
        "rank": 18
      },
      {
        "name": "Bradjones",
        "class": "Warrior",
        "rank": 19
      },
      {
        "name": "Whyu",
        "class": "Rogue",
        "rank": 20
      },
      {
        "name": "Scuffles",
        "class": "Rogue",
        "rank": 21
      },
      {
        "name": "Figro",
        "class": "Rogue",
        "rank": 22
      },
      {
        "name": "Grindpa",
        "class": "Warrior",
        "rank": 23
      },
      {
        "name": "Frostydevito",
        "class": "Mage",
        "rank": 24
      },
      {
        "name": "Kuruptus",
        "class": "Warlock",
        "rank": 25
      },
      {
        "name": "Ninrah",
        "class": "Warrior",
        "rank": 26
      },
      {
        "name": "Acid",
        "class": "Rogue",
        "rank": 27
      },
      {
        "name": "Brosephina",
        "class": "Warrior",
        "rank": 28
      }
    ]
  },
  {
    "id": "44",
    "name": "Gluth Normal",
    "rankings": [
      {
        "name": "Holyymolyy",
        "class": "Priest",
        "rank": 1
      },
      {
        "name": "Moonwell",
        "class": "Druid",
        "rank": 2
      },
      {
        "name": "Dagomi",
        "class": "Paladin",
        "rank": 3
      },
      {
        "name": "Msstorm",
        "class": "Priest",
        "rank": 4
      },
      {
        "name": "Fannia",
        "class": "Druid",
        "rank": 5
      },
      {
        "name": "Aamara",
        "class": "Priest",
        "rank": 6
      },
      {
        "name": "Bunlop",
        "class": "Priest",
        "rank": 7
      },
      {
        "name": "Kasiri",
        "class": "Priest",
        "rank": 8
      },
      {
        "name": "Trendkill",
        "class": "Paladin",
        "rank": 9
      },
      {
        "name": "Shalawam",
        "class": "Priest",
        "rank": 10
      },
      {
        "name": "Snormantha",
        "class": "Priest",
        "rank": 11
      },
      {
        "name": "Palamino",
        "class": "Paladin",
        "rank": 12
      },
      {
        "name": "Smalltime",
        "class": "Warrior",
        "rank": 13
      },
      {
        "name": "Oars",
        "class": "Warrior",
        "rank": 14
      },
      {
        "name": "Kuruptus",
        "class": "Warlock",
        "rank": 15
      },
      {
        "name": "Bradjones",
        "class": "Warrior",
        "rank": 16
      },
      {
        "name": "Loafofbread",
        "class": "Warrior",
        "rank": 17
      },
      {
        "name": "Alexanderr",
        "class": "Warrior",
        "rank": 18
      },
      {
        "name": "Taniel",
        "class": "Warrior",
        "rank": 19
      },
      {
        "name": "Lilianas",
        "class": "Rogue",
        "rank": 20
      },
      {
        "name": "Ninrah",
        "class": "Warrior",
        "rank": 21
      },
      {
        "name": "Brosephina",
        "class": "Warrior",
        "rank": 22
      },
      {
        "name": "Grindpa",
        "class": "Warrior",
        "rank": 23
      },
      {
        "name": "Scuffles",
        "class": "Rogue",
        "rank": 24
      },
      {
        "name": "Iculus",
        "class": "Warrior",
        "rank": 25
      },
      {
        "name": "Figro",
        "class": "Rogue",
        "rank": 26
      }
    ]
  },
  {
    "id": "50",
    "name": "Thaddius Normal",
    "rankings": [
      {
        "name": "Aamara",
        "class": "Priest",
        "rank": 1
      },
      {
        "name": "Dagomi",
        "class": "Paladin",
        "rank": 2
      },
      {
        "name": "Msstorm",
        "class": "Priest",
        "rank": 3
      },
      {
        "name": "Palamino",
        "class": "Paladin",
        "rank": 4
      },
      {
        "name": "Moonwell",
        "class": "Druid",
        "rank": 5
      },
      {
        "name": "Kasiri",
        "class": "Priest",
        "rank": 6
      },
      {
        "name": "Shalawam",
        "class": "Priest",
        "rank": 7
      },
      {
        "name": "Joanofarc",
        "class": "Paladin",
        "rank": 8
      },
      {
        "name": "Fannia",
        "class": "Druid",
        "rank": 9
      },
      {
        "name": "Bunlop",
        "class": "Priest",
        "rank": 10
      },
      {
        "name": "Holyymolyy",
        "class": "Priest",
        "rank": 11
      },
      {
        "name": "Snormantha",
        "class": "Priest",
        "rank": 12
      },
      {
        "name": "Trendkill",
        "class": "Paladin",
        "rank": 13
      },
      {
        "name": "Loafofbread",
        "class": "Warrior",
        "rank": 14
      },
      {
        "name": "Lilianas",
        "class": "Rogue",
        "rank": 15
      },
      {
        "name": "Ninrah",
        "class": "Warrior",
        "rank": 16
      },
      {
        "name": "Brosephina",
        "class": "Warrior",
        "rank": 17
      },
      {
        "name": "Iculus",
        "class": "Warrior",
        "rank": 18
      },
      {
        "name": "Taniel",
        "class": "Warrior",
        "rank": 19
      },
      {
        "name": "Scuffles",
        "class": "Rogue",
        "rank": 20
      },
      {
        "name": "Whyu",
        "class": "Rogue",
        "rank": 21
      },
      {
        "name": "Acid",
        "class": "Rogue",
        "rank": 22
      },
      {
        "name": "Frostydevito",
        "class": "Mage",
        "rank": 23
      },
      {
        "name": "Deadinside",
        "class": "Druid",
        "rank": 24
      },
      {
        "name": "Oars",
        "class": "Warrior",
        "rank": 25
      },
      {
        "name": "Figro",
        "class": "Rogue",
        "rank": 26
      },
      {
        "name": "Grindpa",
        "class": "Warrior",
        "rank": 27
      },
      {
        "name": "Narünn",
        "class": "Druid",
        "rank": 28
      },
      {
        "name": "Bradjones",
        "class": "Warrior",
        "rank": 29
      },
      {
        "name": "Badcandy",
        "class": "Rogue",
        "rank": 30
      },
      {
        "name": "Alexanderr",
        "class": "Warrior",
        "rank": 31
      },
      {
        "name": "Kuruptus",
        "class": "Warlock",
        "rank": 32
      },
      {
        "name": "Frosturself",
        "class": "Mage",
        "rank": 33
      },
      {
        "name": "Kismyleather",
        "class": "Mage",
        "rank": 34
      },
      {
        "name": "Smalltime",
        "class": "Warrior",
        "rank": 35
      },
      {
        "name": "Erma",
        "class": "Mage",
        "rank": 36
      },
      {
        "name": "Chiillii",
        "class": "Mage",
        "rank": 37
      },
      {
        "name": "Nyxie",
        "class": "Hunter",
        "rank": 38
      }
    ]
  },
  {
    "id": "57",
    "name": "Noth the Plaguebringer Normal",
    "rankings": [
      {
        "name": "Palamino",
        "class": "Paladin",
        "rank": 1
      },
      {
        "name": "Dagomi",
        "class": "Paladin",
        "rank": 2
      },
      {
        "name": "Fannia",
        "class": "Druid",
        "rank": 3
      },
      {
        "name": "Holyymolyy",
        "class": "Priest",
        "rank": 4
      },
      {
        "name": "Bunlop",
        "class": "Priest",
        "rank": 5
      },
      {
        "name": "Kasiri",
        "class": "Priest",
        "rank": 6
      },
      {
        "name": "Joanofarc",
        "class": "Paladin",
        "rank": 7
      },
      {
        "name": "Moonwell",
        "class": "Druid",
        "rank": 8
      },
      {
        "name": "Shalawam",
        "class": "Priest",
        "rank": 9
      },
      {
        "name": "Gonk",
        "class": "Rogue",
        "rank": 10
      },
      {
        "name": "Chiillii",
        "class": "Mage",
        "rank": 11
      },
      {
        "name": "Trendkill",
        "class": "Paladin",
        "rank": 12
      },
      {
        "name": "Grindpa",
        "class": "Warrior",
        "rank": 13
      },
      {
        "name": "Loafofbread",
        "class": "Warrior",
        "rank": 14
      },
      {
        "name": "Oars",
        "class": "Warrior",
        "rank": 15
      },
      {
        "name": "Figro",
        "class": "Rogue",
        "rank": 16
      },
      {
        "name": "Snormantha",
        "class": "Priest",
        "rank": 17
      },
      {
        "name": "Lilianas",
        "class": "Rogue",
        "rank": 18
      },
      {
        "name": "Narünn",
        "class": "Druid",
        "rank": 19
      },
      {
        "name": "Taniel",
        "class": "Warrior",
        "rank": 20
      },
      {
        "name": "Smalltime",
        "class": "Warrior",
        "rank": 21
      },
      {
        "name": "Brosephina",
        "class": "Warrior",
        "rank": 22
      },
      {
        "name": "Iculus",
        "class": "Warrior",
        "rank": 23
      },
      {
        "name": "Msstorm",
        "class": "Priest",
        "rank": 24
      },
      {
        "name": "Deadinside",
        "class": "Druid",
        "rank": 25
      },
      {
        "name": "Aamara",
        "class": "Priest",
        "rank": 26
      },
      {
        "name": "Bradjones",
        "class": "Warrior",
        "rank": 27
      },
      {
        "name": "Alexanderr",
        "class": "Warrior",
        "rank": 28
      }
    ]
  },
  {
    "id": "62",
    "name": "Heigan the Unclean Normal",
    "rankings": [
      {
        "name": "Bunlop",
        "class": "Priest",
        "rank": 1
      },
      {
        "name": "Grindpa",
        "class": "Warrior",
        "rank": 2
      },
      {
        "name": "Fannia",
        "class": "Druid",
        "rank": 3
      },
      {
        "name": "Dagomi",
        "class": "Paladin",
        "rank": 4
      },
      {
        "name": "Trendkill",
        "class": "Paladin",
        "rank": 5
      },
      {
        "name": "Kasiri",
        "class": "Priest",
        "rank": 6
      },
      {
        "name": "Msstorm",
        "class": "Priest",
        "rank": 7
      },
      {
        "name": "Palamino",
        "class": "Paladin",
        "rank": 8
      },
      {
        "name": "Ninrah",
        "class": "Warrior",
        "rank": 9
      },
      {
        "name": "Loafofbread",
        "class": "Warrior",
        "rank": 10
      },
      {
        "name": "Moonwell",
        "class": "Druid",
        "rank": 11
      },
      {
        "name": "Oars",
        "class": "Warrior",
        "rank": 12
      },
      {
        "name": "Smalltime",
        "class": "Warrior",
        "rank": 13
      },
      {
        "name": "Iculus",
        "class": "Warrior",
        "rank": 14
      },
      {
        "name": "Brosephina",
        "class": "Warrior",
        "rank": 15
      },
      {
        "name": "Alexanderr",
        "class": "Warrior",
        "rank": 16
      },
      {
        "name": "Holyymolyy",
        "class": "Priest",
        "rank": 17
      },
      {
        "name": "Taniel",
        "class": "Warrior",
        "rank": 18
      },
      {
        "name": "Snormantha",
        "class": "Priest",
        "rank": 19
      },
      {
        "name": "Bradjones",
        "class": "Warrior",
        "rank": 20
      },
      {
        "name": "Gonk",
        "class": "Rogue",
        "rank": 21
      },
      {
        "name": "Lilianas",
        "class": "Rogue",
        "rank": 22
      },
      {
        "name": "Scuffles",
        "class": "Rogue",
        "rank": 23
      },
      {
        "name": "Joanofarc",
        "class": "Paladin",
        "rank": 24
      },
      {
        "name": "Shalawam",
        "class": "Priest",
        "rank": 25
      },
      {
        "name": "Figro",
        "class": "Rogue",
        "rank": 26
      },
      {
        "name": "Whyu",
        "class": "Rogue",
        "rank": 27
      },
      {
        "name": "Narünn",
        "class": "Druid",
        "rank": 28
      },
      {
        "name": "Acid",
        "class": "Rogue",
        "rank": 29
      },
      {
        "name": "Badcandy",
        "class": "Rogue",
        "rank": 30
      },
      {
        "name": "Angelmae",
        "class": "Hunter",
        "rank": 31
      },
      {
        "name": "Kuruptus",
        "class": "Warlock",
        "rank": 32
      },
      {
        "name": "Chiillii",
        "class": "Mage",
        "rank": 33
      },
      {
        "name": "Deadinside",
        "class": "Druid",
        "rank": 34
      },
      {
        "name": "Frostydevito",
        "class": "Mage",
        "rank": 35
      },
      {
        "name": "Aamara",
        "class": "Priest",
        "rank": 36
      },
      {
        "name": "Frosturself",
        "class": "Mage",
        "rank": 37
      },
      {
        "name": "Erma",
        "class": "Mage",
        "rank": 38
      },
      {
        "name": "Nyxie",
        "class": "Hunter",
        "rank": 39
      },
      {
        "name": "Kismyleather",
        "class": "Mage",
        "rank": 40
      }
    ]
  },
  {
    "id": "64",
    "name": "Loatheb Normal",
    "rankings": [
      {
        "name": "Bunlop",
        "class": "Priest",
        "rank": 1
      },
      {
        "name": "Holyymolyy",
        "class": "Priest",
        "rank": 2
      },
      {
        "name": "Palamino",
        "class": "Paladin",
        "rank": 3
      },
      {
        "name": "Dagomi",
        "class": "Paladin",
        "rank": 4
      },
      {
        "name": "Aamara",
        "class": "Priest",
        "rank": 5
      },
      {
        "name": "Msstorm",
        "class": "Priest",
        "rank": 6
      },
      {
        "name": "Joanofarc",
        "class": "Paladin",
        "rank": 7
      },
      {
        "name": "Fannia",
        "class": "Druid",
        "rank": 8
      },
      {
        "name": "Moonwell",
        "class": "Druid",
        "rank": 9
      },
      {
        "name": "Shalawam",
        "class": "Priest",
        "rank": 10
      },
      {
        "name": "Trendkill",
        "class": "Paladin",
        "rank": 11
      },
      {
        "name": "Kasiri",
        "class": "Priest",
        "rank": 12
      },
      {
        "name": "Snormantha",
        "class": "Priest",
        "rank": 13
      },
      {
        "name": "Grindpa",
        "class": "Warrior",
        "rank": 14
      },
      {
        "name": "Smalltime",
        "class": "Warrior",
        "rank": 15
      },
      {
        "name": "Iculus",
        "class": "Warrior",
        "rank": 16
      },
      {
        "name": "Alexanderr",
        "class": "Warrior",
        "rank": 17
      },
      {
        "name": "Ninrah",
        "class": "Warrior",
        "rank": 18
      },
      {
        "name": "Oars",
        "class": "Warrior",
        "rank": 19
      },
      {
        "name": "Taniel",
        "class": "Warrior",
        "rank": 20
      },
      {
        "name": "Brosephina",
        "class": "Warrior",
        "rank": 21
      },
      {
        "name": "Loafofbread",
        "class": "Warrior",
        "rank": 22
      },
      {
        "name": "Lilianas",
        "class": "Rogue",
        "rank": 23
      },
      {
        "name": "Bradjones",
        "class": "Warrior",
        "rank": 24
      },
      {
        "name": "Gonk",
        "class": "Rogue",
        "rank": 25
      }
    ]
  },
  {
    "id": "69",
    "name": "AnubRekhan Normal",
    "rankings": [
      {
        "name": "Bunlop",
        "class": "Priest",
        "rank": 1
      },
      {
        "name": "Holyymolyy",
        "class": "Priest",
        "rank": 2
      },
      {
        "name": "Palamino",
        "class": "Paladin",
        "rank": 3
      },
      {
        "name": "Dagomi",
        "class": "Paladin",
        "rank": 4
      },
      {
        "name": "Aamara",
        "class": "Priest",
        "rank": 5
      },
      {
        "name": "Msstorm",
        "class": "Priest",
        "rank": 6
      },
      {
        "name": "Joanofarc",
        "class": "Paladin",
        "rank": 7
      },
      {
        "name": "Fannia",
        "class": "Druid",
        "rank": 8
      },
      {
        "name": "Moonwell",
        "class": "Druid",
        "rank": 9
      },
      {
        "name": "Shalawam",
        "class": "Priest",
        "rank": 10
      },
      {
        "name": "Trendkill",
        "class": "Paladin",
        "rank": 11
      },
      {
        "name": "Kasiri",
        "class": "Priest",
        "rank": 12
      },
      {
        "name": "Snormantha",
        "class": "Priest",
        "rank": 13
      },
      {
        "name": "Grindpa",
        "class": "Warrior",
        "rank": 14
      },
      {
        "name": "Smalltime",
        "class": "Warrior",
        "rank": 15
      },
      {
        "name": "Iculus",
        "class": "Warrior",
        "rank": 16
      },
      {
        "name": "Alexanderr",
        "class": "Warrior",
        "rank": 17
      },
      {
        "name": "Ninrah",
        "class": "Warrior",
        "rank": 18
      },
      {
        "name": "Oars",
        "class": "Warrior",
        "rank": 19
      },
      {
        "name": "Taniel",
        "class": "Warrior",
        "rank": 20
      },
      {
        "name": "Brosephina",
        "class": "Warrior",
        "rank": 21
      },
      {
        "name": "Loafofbread",
        "class": "Warrior",
        "rank": 22
      },
      {
        "name": "Lilianas",
        "class": "Rogue",
        "rank": 23
      },
      {
        "name": "Bradjones",
        "class": "Warrior",
        "rank": 24
      },
      {
        "name": "Gonk",
        "class": "Rogue",
        "rank": 25
      }
    ]
  },
  {
    "id": "90",
    "name": "Grand Widow Faerlina Normal",
    "rankings": [
      {
        "name": "Holyymolyy",
        "class": "Priest",
        "rank": 1
      },
      {
        "name": "Msstorm",
        "class": "Priest",
        "rank": 2
      },
      {
        "name": "Shalawam",
        "class": "Priest",
        "rank": 3
      },
      {
        "name": "Bunlop",
        "class": "Priest",
        "rank": 4
      },
      {
        "name": "Aamara",
        "class": "Priest",
        "rank": 5
      },
      {
        "name": "Snormantha",
        "class": "Priest",
        "rank": 6
      },
      {
        "name": "Kasiri",
        "class": "Priest",
        "rank": 7
      },
      {
        "name": "Palamino",
        "class": "Paladin",
        "rank": 8
      },
      {
        "name": "Moonwell",
        "class": "Druid",
        "rank": 9
      },
      {
        "name": "Dagomi",
        "class": "Paladin",
        "rank": 10
      },
      {
        "name": "Joanofarc",
        "class": "Paladin",
        "rank": 11
      },
      {
        "name": "Fannia",
        "class": "Druid",
        "rank": 12
      },
      {
        "name": "Trendkill",
        "class": "Paladin",
        "rank": 13
      },
      {
        "name": "Grindpa",
        "class": "Warrior",
        "rank": 14
      },
      {
        "name": "Oars",
        "class": "Warrior",
        "rank": 15
      },
      {
        "name": "Ninrah",
        "class": "Warrior",
        "rank": 16
      },
      {
        "name": "Chiillii",
        "class": "Mage",
        "rank": 17
      },
      {
        "name": "Gonk",
        "class": "Rogue",
        "rank": 18
      },
      {
        "name": "Lilianas",
        "class": "Rogue",
        "rank": 19
      },
      {
        "name": "Deadinside",
        "class": "Druid",
        "rank": 20
      },
      {
        "name": "Taniel",
        "class": "Warrior",
        "rank": 21
      },
      {
        "name": "Figro",
        "class": "Rogue",
        "rank": 22
      },
      {
        "name": "Smalltime",
        "class": "Warrior",
        "rank": 23
      },
      {
        "name": "Brosephina",
        "class": "Warrior",
        "rank": 24
      },
      {
        "name": "Iculus",
        "class": "Warrior",
        "rank": 25
      },
      {
        "name": "Loafofbread",
        "class": "Warrior",
        "rank": 26
      },
      {
        "name": "Bradjones",
        "class": "Warrior",
        "rank": 27
      },
      {
        "name": "Alexanderr",
        "class": "Warrior",
        "rank": 28
      },
      {
        "name": "Acid",
        "class": "Rogue",
        "rank": 29
      },
      {
        "name": "Badcandy",
        "class": "Rogue",
        "rank": 30
      }
    ]
  },
  {
    "id": "97",
    "name": "Maexxna Normal",
    "rankings": [
      {
        "name": "Holyymolyy",
        "class": "Priest",
        "rank": 1
      },
      {
        "name": "Dagomi",
        "class": "Paladin",
        "rank": 2
      },
      {
        "name": "Fannia",
        "class": "Druid",
        "rank": 3
      },
      {
        "name": "Shalawam",
        "class": "Priest",
        "rank": 4
      },
      {
        "name": "Palamino",
        "class": "Paladin",
        "rank": 5
      },
      {
        "name": "Joanofarc",
        "class": "Paladin",
        "rank": 6
      },
      {
        "name": "Moonwell",
        "class": "Druid",
        "rank": 7
      },
      {
        "name": "Snormantha",
        "class": "Priest",
        "rank": 8
      },
      {
        "name": "Kasiri",
        "class": "Priest",
        "rank": 9
      },
      {
        "name": "Narünn",
        "class": "Druid",
        "rank": 10
      },
      {
        "name": "Kuruptus",
        "class": "Warlock",
        "rank": 11
      },
      {
        "name": "Bradjones",
        "class": "Warrior",
        "rank": 12
      },
      {
        "name": "Ninrah",
        "class": "Warrior",
        "rank": 13
      },
      {
        "name": "Smalltime",
        "class": "Warrior",
        "rank": 14
      },
      {
        "name": "Grindpa",
        "class": "Warrior",
        "rank": 15
      },
      {
        "name": "Iculus",
        "class": "Warrior",
        "rank": 16
      },
      {
        "name": "Oars",
        "class": "Warrior",
        "rank": 17
      }
    ]
  },
  {
    "id": "last",
    "name": "Instructor Razuvious Normal",
    "rankings": [
      {
        "name": "Holyymolyy",
        "class": "Priest",
        "rank": 1
      },
      {
        "name": "Dagomi",
        "class": "Paladin",
        "rank": 2
      },
      {
        "name": "Fannia",
        "class": "Druid",
        "rank": 3
      },
      {
        "name": "Shalawam",
        "class": "Priest",
        "rank": 4
      },
      {
        "name": "Palamino",
        "class": "Paladin",
        "rank": 5
      },
      {
        "name": "Joanofarc",
        "class": "Paladin",
        "rank": 6
      },
      {
        "name": "Moonwell",
        "class": "Druid",
        "rank": 7
      },
      {
        "name": "Snormantha",
        "class": "Priest",
        "rank": 8
      },
      {
        "name": "Kasiri",
        "class": "Priest",
        "rank": 9
      },
      {
        "name": "Narünn",
        "class": "Druid",
        "rank": 10
      },
      {
        "name": "Kuruptus",
        "class": "Warlock",
        "rank": 11
      },
      {
        "name": "Bradjones",
        "class": "Warrior",
        "rank": 12
      },
      {
        "name": "Ninrah",
        "class": "Warrior",
        "rank": 13
      },
      {
        "name": "Smalltime",
        "class": "Warrior",
        "rank": 14
      },
      {
        "name": "Grindpa",
        "class": "Warrior",
        "rank": 15
      },
      {
        "name": "Iculus",
        "class": "Warrior",
        "rank": 16
      },
      {
        "name": "Oars",
        "class": "Warrior",
        "rank": 17
      }
    ]
  }
]